pyPhoenix-0.12.0.dist-info/METADATA
pyPhoenix-0.12.0.dist-info/RECORD
pyPhoenix-0.12.0.dist-info/WHEEL
pyPhoenix-0.12.0.dist-info/entry_points.txt
pyPhoenix-0.12.0.dist-info/top_level.txt
pyphoenix/__init__.py
pyphoenix/avatica.py
pyphoenix/common_pb2.py
pyphoenix/connection.py
pyphoenix/cursor.py
pyphoenix/errors.py
pyphoenix/requests_pb2.py
pyphoenix/responses_pb2.py
pyphoenix/sqlalchemy_phoenix.py
pyphoenix/types.py
pyphoenix/tests/__init__.py
pyphoenix/tests/dbapi20.py
pyphoenix/tests/test_avatica.py
pyphoenix/tests/test_dbapi20.py
pyphoenix/tests/test_errors.py
pyphoenix/tests/test_types.py
