Metadata-Version: 2.1
Name: pyPhoenix
Version: 0.12.0
Summary: python interface to Phoenix and SQLAlchemy interfaces
Home-page: https://github.com/Pirionfr/pyPhoenix
Author: Dimitri Capitaine
Author-email: grytes29@gmail.com
License: Apache 2
Platform: UNKNOWN
Classifier: Programming Language :: Python :: 2.7
Classifier: Programming Language :: Python :: 3.5
Classifier: Programming Language :: Python :: 3.6
Requires-Dist: protobuf
Requires-Dist: sqlalchemy
Requires-Dist: future
